cx_autopos.cpython-38-x86_64-linux-gnu.so
cx_debug_engine.cpython-38-x86_64-linux-gnu.so
cx_packets.cpython-38-x86_64-linux-gnu.so
cx_engine.cpython-38-x86_64-linux-gnu.so
rtloc_manager-0.1.2.dist-info/top_level.txt
rtloc_manager-0.1.2.dist-info/METADATA
rtloc_manager-0.1.2.dist-info/RECORD
rtloc_manager-0.1.2.dist-info/WHEEL
rtloc_manager/manager_api.py
rtloc_manager/__init__.py
rtloc_manager/database.py
rtloc_manager/manager.py
rtloc_manager/manager_config.py
rtloc_manager/frontend/__init__.py
rtloc_manager/frontend/frontend.py
rtloc_manager/frontend/workers.py
rtloc_manager/frontend/ui/rtloc.py
rtloc_manager/frontend/ui/__init__.py
rtloc_manager/frontend/img/forklift.png
rtloc_manager/utils/firmware_update.py
rtloc_manager/utils/__init__.py
rtloc_manager/utils/event_offloading.py
rtloc_manager/bin/libzmq-68c212d3.so.5.2.4
rtloc_manager/bin/parser_exec.sh
rtloc_manager/bin/.gitkeep
rtloc_manager/bin/libsodium-6eb86948.so.23.3.0
rtloc_manager/bin/parser
rtloc_manager/apps/__init__.py
rtloc_manager/apps/position_log_app.py
rtloc_manager/apps/position_print_app.py
rtloc_manager/apps/distance_grid_app.py
rtloc_manager/apps/mqtt_publish_app.py
rtloc_manager/core/engine.py
rtloc_manager/core/__init__.py
rtloc_manager/core/autopos.py
rtloc_manager/interfaces/__init__.py
rtloc_manager/interfaces/uart.py
rtloc_manager/interfaces/listener.py
rtloc_manager.libs/libzmq-68c212d3-3b1a8d44.so.5.2.4
rtloc_manager.libs/libsodium-6eb86948-f4cdbc1f.so.23.3.0
