Metadata-Version: 2.1
Name: rtloc-manager
Version: 0.1.2
Summary: rtloc manager library
Home-page: UNKNOWN
Author: Jasper Wouters @ RTLOC
Author-email: jasper@rtloc.com
License: UNKNOWN
Platform: UNKNOWN
Requires-Python: >=3.6
Requires-Dist: PyYAML
Requires-Dist: bunch
Requires-Dist: numpy
Requires-Dist: scipy
Requires-Dist: flask
Requires-Dist: paho-mqtt
Requires-Dist: PySide2
Requires-Dist: pyqtgraph
Requires-Dist: QDarkStyle
Requires-Dist: pyzmq (==22.3.0)
